acme_s3/__init__.py
acme_s3/_main.py
acme_s3/s3.py
acme_s3/s3bench.py
acme_s3-0.0.5.dist-info/METADATA
acme_s3-0.0.5.dist-info/WHEEL
acme_s3-0.0.5.dist-info/entry_points.txt
acme_s3-0.0.5.dist-info/top_level.txt
acme_s3-0.0.5.dist-info/RECORD
