Metadata-Version: 2.2
Name: acme_s3
Version: 0.0.5
Summary: Efficient access to S3
Author-email: guner.stan@gmail.com
Project-URL: homepage, https://example.com
Project-URL: repository, https://example.com
Classifier: Programming Language :: Python :: 3.12
Requires-Dist: python-dotenv
Requires-Dist: boto3
Requires-Dist: tqdm
Requires-Dist: backoff
Requires-Dist: botocore
Requires-Dist: pandas
Provides-Extra: dev
Requires-Dist: pytest; extra == "dev"
Requires-Dist: uv; extra == "dev"
Requires-Dist: mkdocs; extra == "dev"
Requires-Dist: mkdocs-material; extra == "dev"
Requires-Dist: mkdocstrings[python]; extra == "dev"
Requires-Dist: jupyterlab; extra == "dev"
Requires-Dist: isort; extra == "dev"
